{
  "ok": true,
  "date": "2026-01-07",
  "tickerOffset": 0,
  "tickerBatch": 4,
  "tickersProcessed": 4,
  "intervals": 14,
  "intervalMinutes": 30,
  "scored": 27,
  "skipped": 0,
  "tradesCreated": 0,
  "totalTrades": 0,
  "hasMore": false,
  "nextTickerOffset": null,
  "errorsCount": 29,
  "errors": [
    {
      "ticker": "SPY",
      "ts": 1767796200000,
      "error": "Cannot access '_tickerUpperEarly' before initialization"
    },
    {
      "ticker": "IWM",
      "ts": 1767796200000,
      "error": "Cannot access '_tickerUpperEarly' before initialization"
    },
    {
      "ticker": "SPY",
      "ts": 1767798000000,
      "error": "Cannot access '_tickerUpperEarly' before initialization"
    },
    {
      "ticker": "SPY",
      "ts": 1767799800000,
      "error": "Cannot access '_tickerUpperEarly' before initialization"
    },
    {
      "ticker": "IWM",
      "ts": 1767799800000,
      "error": "Cannot access '_tickerUpperEarly' before initialization"
    },
    {
      "ticker": "SPY",
      "ts": 1767801600000,
      "error": "Cannot access '_tickerUpperEarly' before initialization"
    },
    {
      "ticker": "QQQ",
      "ts": 1767801600000,
      "error": "Cannot access '_tickerUpperEarly' before initialization"
    },
    {
      "ticker": "SPY",
      "ts": 1767803400000,
      "error": "Cannot access '_tickerUpperEarly' before initialization"
    },
    {
      "ticker": "QQQ",
      "ts": 1767803400000,
      "error": "Cannot access '_tickerUpperEarly' before initialization"
    },
    {
      "ticker": "SPY",
      "ts": 1767805200000,
      "error": "Cannot access '_tickerUpperEarly' before initialization"
    }
  ],
  "stageCounts": {
    "watch": 21,
    "setup": 6
  },
  "blockReasons": {
    "h3_rank_below_transitional_floor": 24,
    "rvol_dead_zone": 3
  },
  "d1StateWritten": 4,
  "trailWritten": 27,
  "lastSnapshot": {
    "SPY": {
      "state": "HTF_BULL_LTF_PULLBACK",
      "htf_score": 43.4,
      "ltf_score": -12.9,
      "ema_regime_daily": 2,
      "ema_regime_4h": 2,
      "fuel_D": 82,
      "fuel_10": 62,
      "fuel_30": 77,
      "st_support_D": {
        "dir": "bull",
        "slope": "rising",
        "aligned": true
      },
      "kanban_stage": "watch",
      "score": 87,
      "block_reason": null,
      "block_fuel_pct": null,
      "primary_fuel": 77
    },
    "QQQ": {
      "state": "HTF_BULL_LTF_BULL",
      "htf_score": 39.9,
      "ltf_score": 1.1,
      "ema_regime_daily": 2,
      "ema_regime_4h": 2,
      "fuel_D": 79,
      "fuel_10": 45,
      "fuel_30": 90,
      "st_support_D": {
        "dir": "bear",
        "slope": "flat",
        "aligned": true
      },
      "kanban_stage": "watch",
      "score": 71,
      "block_reason": null,
      "block_fuel_pct": null,
      "primary_fuel": 90
    },
    "IWM": {
      "state": "HTF_BULL_LTF_BULL",
      "htf_score": 41.4,
      "ltf_score": 3.7,
      "ema_regime_daily": 2,
      "ema_regime_4h": 2,
      "fuel_D": 66,
      "fuel_10": 99,
      "fuel_30": 97,
      "st_support_D": {
        "dir": "bull",
        "slope": "rising",
        "aligned": true
      },
      "kanban_stage": "watch",
      "score": 90,
      "block_reason": null,
      "block_fuel_pct": null,
      "primary_fuel": 99
    },
    "DIA": {
      "state": "HTF_BULL_LTF_PULLBACK",
      "htf_score": 40.7,
      "ltf_score": -21.7,
      "ema_regime_daily": 2,
      "ema_regime_4h": 2,
      "fuel_D": 74,
      "fuel_10": 22,
      "fuel_30": 21,
      "st_support_D": {
        "dir": "bull",
        "slope": "flat",
        "aligned": true
      },
      "kanban_stage": "watch",
      "score": 77,
      "block_reason": null,
      "block_fuel_pct": null,
      "primary_fuel": 22
    }
  },
  "targetSnapshots": {},
  "targetTimeline": [],
  "processDebug": [],
  "blockedEntryGates": {
    "h3_rank_below_transitional_floor": 48,
    "_total": 54,
    "rvol_dead_zone": 6
  },
  "blockChainBars": [
    {
      "ticker": "QQQ",
      "ts": 1767796200000,
      "reason": "h3_rank_below_transitional_floor",
      "kanban_stage": "watch",
      "state": "HTF_BULL_LTF_BULL",
      "score": 85,
      "rank": 85,
      "htf_score": 40,
      "ltf_score": 18,
      "daily_structure": {
        "px": 624.02,
        "e21": 619.48,
        "e48": 617.88,
        "e200": 600.71,
        "pct_above_e48": 0.99,
        "pct_above_e21": 0.73,
        "e21_slope_5d_pct": 0.33,
        "e48_slope_10d_pct": 0.1,
        "bull_stack": true,
        "bear_stack": false,
        "above_e200": true
      },
      "index_etf_swing_diag": null
    },
    {
      "ticker": "DIA",
      "ts": 1767796200000,
      "reason": "h3_rank_below_transitional_floor",
      "kanban_stage": "watch",
      "state": "HTF_BULL_LTF_BULL",
      "score": 67,
      "rank": 67,
      "htf_score": 41.5,
      "ltf_score": 2.4,
      "daily_structure": {
        "px": 489.96,
        "e21": 486.78,
        "e48": 483.15,
        "e200": 468.57,
        "pct_above_e48": 1.41,
        "pct_above_e21": 0.65,
        "e21_slope_5d_pct": 0.62,
        "e48_slope_10d_pct": 0.54,
        "bull_stack": true,
        "bear_stack": false,
        "above_e200": true
      },
      "index_etf_swing_diag": null
    },
    {
      "ticker": "QQQ",
      "ts": 1767798000000,
      "reason": "h3_rank_below_transitional_floor",
      "kanban_stage": "watch",
      "state": "HTF_BULL_LTF_BULL",
      "score": 79,
      "rank": 79,
      "htf_score": 40,
      "ltf_score": 16.8,
      "daily_structure": {
        "px": 624.02,
        "e21": 619.48,
        "e48": 617.88,
        "e200": 600.71,
        "pct_above_e48": 0.99,
        "pct_above_e21": 0.73,
        "e21_slope_5d_pct": 0.33,
        "e48_slope_10d_pct": 0.1,
        "bull_stack": true,
        "bear_stack": false,
        "above_e200": true
      },
      "index_etf_swing_diag": null
    },
    {
      "ticker": "IWM",
      "ts": 1767798000000,
      "reason": "h3_rank_below_transitional_floor",
      "kanban_stage": "setup",
      "state": "HTF_BULL_LTF_PULLBACK",
      "score": 74,
      "rank": 74,
      "htf_score": 39.8,
      "ltf_score": -4.9,
      "daily_structure": {
        "px": 255.48,
        "e21": 251.93,
        "e48": 250.29,
        "e200": 241.86,
        "pct_above_e48": 2.07,
        "pct_above_e21": 1.41,
        "e21_slope_5d_pct": 0.81,
        "e48_slope_10d_pct": 0.41,
        "bull_stack": true,
        "bear_stack": false,
        "above_e200": true
      },
      "index_etf_swing_diag": null
    },
    {
      "ticker": "DIA",
      "ts": 1767798000000,
      "reason": "h3_rank_below_transitional_floor",
      "kanban_stage": "watch",
      "state": "HTF_BULL_LTF_PULLBACK",
      "score": 63,
      "rank": 63,
      "htf_score": 41.5,
      "ltf_score": -12.6,
      "daily_structure": {
        "px": 489.96,
        "e21": 486.78,
        "e48": 483.15,
        "e200": 468.57,
        "pct_above_e48": 1.41,
        "pct_above_e21": 0.65,
        "e21_slope_5d_pct": 0.62,
        "e48_slope_10d_pct": 0.54,
        "bull_stack": true,
        "bear_stack": false,
        "above_e200": true
      },
      "index_etf_swing_diag": null
    },
    {
      "ticker": "QQQ",
      "ts": 1767799800000,
      "reason": "h3_rank_below_transitional_floor",
      "kanban_stage": "watch",
      "state": "HTF_BULL_LTF_BULL",
      "score": 75,
      "rank": 75,
      "htf_score": 40,
      "ltf_score": 16.7,
      "daily_structure": {
        "px": 624.02,
        "e21": 619.48,
        "e48": 617.88,
        "e200": 600.71,
        "pct_above_e48": 0.99,
        "pct_above_e21": 0.73,
        "e21_slope_5d_pct": 0.33,
        "e48_slope_10d_pct": 0.1,
        "bull_stack": true,
        "bear_stack": false,
        "above_e200": true
      },
      "index_etf_swing_diag": null
    },
    {
      "ticker": "DIA",
      "ts": 1767799800000,
      "reason": "h3_rank_below_transitional_floor",
      "kanban_stage": "setup",
      "state": "HTF_BULL_LTF_PULLBACK",
      "score": 53,
      "rank": 53,
      "htf_score": 41.5,
      "ltf_score": -10,
      "daily_structure": {
        "px": 489.96,
        "e21": 486.78,
        "e48": 483.15,
        "e200": 468.57,
        "pct_above_e48": 1.41,
        "pct_above_e21": 0.65,
        "e21_slope_5d_pct": 0.62,
        "e48_slope_10d_pct": 0.54,
        "bull_stack": true,
        "bear_stack": false,
        "above_e200": true
      },
      "index_etf_swing_diag": null
    },
    {
      "ticker": "IWM",
      "ts": 1767801600000,
      "reason": "h3_rank_below_transitional_floor",
      "kanban_stage": "watch",
      "state": "HTF_BULL_LTF_BULL",
      "score": 89,
      "rank": 89,
      "htf_score": 39.8,
      "ltf_score": 5.6,
      "daily_structure": {
        "px": 255.48,
        "e21": 251.93,
        "e48": 250.29,
        "e200": 241.86,
        "pct_above_e48": 2.07,
        "pct_above_e21": 1.41,
        "e21_slope_5d_pct": 0.81,
        "e48_slope_10d_pct": 0.41,
        "bull_stack": true,
        "bear_stack": false,
        "above_e200": true
      },
      "index_etf_swing_diag": null
    },
    {
      "ticker": "DIA",
      "ts": 1767801600000,
      "reason": "h3_rank_below_transitional_floor",
      "kanban_stage": "setup",
      "state": "HTF_BULL_LTF_PULLBACK",
      "score": 56,
      "rank": 56,
      "htf_score": 41.5,
      "ltf_score": -1,
      "daily_structure": {
        "px": 489.96,
        "e21": 486.78,
        "e48": 483.15,
        "e200": 468.57,
        "pct_above_e48": 1.41,
        "pct_above_e21": 0.65,
        "e21_slope_5d_pct": 0.62,
        "e48_slope_10d_pct": 0.54,
        "bull_stack": true,
        "bear_stack": false,
        "above_e200": true
      },
      "index_etf_swing_diag": null
    },
    {
      "ticker": "IWM",
      "ts": 1767803400000,
      "reason": "h3_rank_below_transitional_floor",
      "kanban_stage": "watch",
      "state": "HTF_BULL_LTF_BULL",
      "score": 86,
      "rank": 86,
      "htf_score": 39.8,
      "ltf_score": 10.4,
      "daily_structure": {
        "px": 255.48,
        "e21": 251.93,
        "e48": 250.29,
        "e200": 241.86,
        "pct_above_e48": 2.07,
        "pct_above_e21": 1.41,
        "e21_slope_5d_pct": 0.81,
        "e48_slope_10d_pct": 0.41,
        "bull_stack": true,
        "bear_stack": false,
        "above_e200": true
      },
      "index_etf_swing_diag": null
    },
    {
      "ticker": "DIA",
      "ts": 1767803400000,
      "reason": "h3_rank_below_transitional_floor",
      "kanban_stage": "watch",
      "state": "HTF_BULL_LTF_BULL",
      "score": 71,
      "rank": 71,
      "htf_score": 41.5,
      "ltf_score": 2.7,
      "daily_structure": {
        "px": 489.96,
        "e21": 486.78,
        "e48": 483.15,
        "e200": 468.57,
        "pct_above_e48": 1.41,
        "pct_above_e21": 0.65,
        "e21_slope_5d_pct": 0.62,
        "e48_slope_10d_pct": 0.54,
        "bull_stack": true,
        "bear_stack": false,
        "above_e200": true
      },
      "index_etf_swing_diag": null
    },
    {
      "ticker": "IWM",
      "ts": 1767805200000,
      "reason": "h3_rank_below_transitional_floor",
      "kanban_stage": "watch",
      "state": "HTF_BULL_LTF_BULL",
      "score": 86,
      "rank": 86,
      "htf_score": 39.8,
      "ltf_score": 9.6,
      "daily_structure": {
        "px": 255.48,
        "e21": 251.93,
        "e48": 250.29,
        "e200": 241.86,
        "pct_above_e48": 2.07,
        "pct_above_e21": 1.41,
        "e21_slope_5d_pct": 0.81,
        "e48_slope_10d_pct": 0.41,
        "bull_stack": true,
        "bear_stack": false,
        "above_e200": true
      },
      "index_etf_swing_diag": null
    },
    {
      "ticker": "DIA",
      "ts": 1767805200000,
      "reason": "h3_rank_below_transitional_floor",
      "kanban_stage": "setup",
      "state": "HTF_BULL_LTF_PULLBACK",
      "score": 63,
      "rank": 63,
      "htf_score": 41.5,
      "ltf_score": -1.1,
      "daily_structure": {
        "px": 489.96,
        "e21": 486.78,
        "e48": 483.15,
        "e200": 468.57,
        "pct_above_e48": 1.41,
        "pct_above_e21": 0.65,
        "e21_slope_5d_pct": 0.62,
        "e48_slope_10d_pct": 0.54,
        "bull_stack": true,
        "bear_stack": false,
        "above_e200": true
      },
      "index_etf_swing_diag": null
    },
    {
      "ticker": "IWM",
      "ts": 1767807000000,
      "reason": "h3_rank_below_transitional_floor",
      "kanban_stage": "watch",
      "state": "HTF_BULL_LTF_BULL",
      "score": 85,
      "rank": 85,
      "htf_score": 39.8,
      "ltf_score": 3.6,
      "daily_structure": {
        "px": 255.48,
        "e21": 251.93,
        "e48": 250.29,
        "e200": 241.86,
        "pct_above_e48": 2.07,
        "pct_above_e21": 1.41,
        "e21_slope_5d_pct": 0.81,
        "e48_slope_10d_pct": 0.41,
        "bull_stack": true,
        "bear_stack": false,
        "above_e200": true
      },
      "index_etf_swing_diag": null
    },
    {
      "ticker": "DIA",
      "ts": 1767807000000,
      "reason": "h3_rank_below_transitional_floor",
      "kanban_stage": "setup",
      "state": "HTF_BULL_LTF_PULLBACK",
      "score": 54,
      "rank": 54,
      "htf_score": 41.5,
      "ltf_score": -8.2,
      "daily_structure": {
        "px": 489.96,
        "e21": 486.78,
        "e48": 483.15,
        "e200": 468.57,
        "pct_above_e48": 1.41,
        "pct_above_e21": 0.65,
        "e21_slope_5d_pct": 0.62,
        "e48_slope_10d_pct": 0.54,
        "bull_stack": true,
        "bear_stack": false,
        "above_e200": true
      },
      "index_etf_swing_diag": null
    },
    {
      "ticker": "IWM",
      "ts": 1767808800000,
      "reason": "h3_rank_below_transitional_floor",
      "kanban_stage": "watch",
      "state": "HTF_BULL_LTF_BULL",
      "score": 89,
      "rank": 89,
      "htf_score": 39.8,
      "ltf_score": 4,
      "daily_structure": {
        "px": 255.48,
        "e21": 251.93,
        "e48": 250.29,
        "e200": 241.86,
        "pct_above_e48": 2.07,
        "pct_above_e21": 1.41,
        "e21_slope_5d_pct": 0.81,
        "e48_slope_10d_pct": 0.41,
        "bull_stack": true,
        "bear_stack": false,
        "above_e200": true
      },
      "index_etf_swing_diag": null
    },
    {
      "ticker": "DIA",
      "ts": 1767808800000,
      "reason": "h3_rank_below_transitional_floor",
      "kanban_stage": "watch",
      "state": "HTF_BULL_LTF_PULLBACK",
      "score": 55,
      "rank": 55,
      "htf_score": 41.5,
      "ltf_score": -14.5,
      "daily_structure": {
        "px": 489.96,
        "e21": 486.78,
        "e48": 483.15,
        "e200": 468.57,
        "pct_above_e48": 1.41,
        "pct_above_e21": 0.65,
        "e21_slope_5d_pct": 0.62,
        "e48_slope_10d_pct": 0.54,
        "bull_stack": true,
        "bear_stack": false,
        "above_e200": true
      },
      "index_etf_swing_diag": null
    },
    {
      "ticker": "IWM",
      "ts": 1767810600000,
      "reason": "h3_rank_below_transitional_floor",
      "kanban_stage": "setup",
      "state": "HTF_BULL_LTF_PULLBACK",
      "score": 80,
      "rank": 80,
      "htf_score": 41.4,
      "ltf_score": -0.8,
      "daily_structure": {
        "px": 255.48,
        "e21": 251.93,
        "e48": 250.29,
        "e200": 241.86,
        "pct_above_e48": 2.07,
        "pct_above_e21": 1.41,
        "e21_slope_5d_pct": 0.81,
        "e48_slope_10d_pct": 0.41,
        "bull_stack": true,
        "bear_stack": false,
        "above_e200": true
      },
      "index_etf_swing_diag": null
    },
    {
      "ticker": "DIA",
      "ts": 1767810600000,
      "reason": "h3_rank_below_transitional_floor",
      "kanban_stage": "watch",
      "state": "HTF_BULL_LTF_PULLBACK",
      "score": 64,
      "rank": 64,
      "htf_score": 40.7,
      "ltf_score": -18.1,
      "daily_structure": {
        "px": 489.96,
        "e21": 486.78,
        "e48": 483.15,
        "e200": 468.57,
        "pct_above_e48": 1.41,
        "pct_above_e21": 0.65,
        "e21_slope_5d_pct": 0.62,
        "e48_slope_10d_pct": 0.54,
        "bull_stack": true,
        "bear_stack": false,
        "above_e200": true
      },
      "index_etf_swing_diag": null
    },
    {
      "ticker": "IWM",
      "ts": 1767812400000,
      "reason": "h3_rank_below_transitional_floor",
      "kanban_stage": "watch",
      "state": "HTF_BULL_LTF_BULL",
      "score": 90,
      "rank": 90,
      "htf_score": 41.4,
      "ltf_score": 3,
      "daily_structure": {
        "px": 255.48,
        "e21": 251.93,
        "e48": 250.29,
        "e200": 241.86,
        "pct_above_e48": 2.07,
        "pct_above_e21": 1.41,
        "e21_slope_5d_pct": 0.81,
        "e48_slope_10d_pct": 0.41,
        "bull_stack": true,
        "bear_stack": false,
        "above_e200": true
      },
      "index_etf_swing_diag": null
    },
    {
      "ticker": "DIA",
      "ts": 1767812400000,
      "reason": "h3_rank_below_transitional_floor",
      "kanban_stage": "watch",
      "state": "HTF_BULL_LTF_PULLBACK",
      "score": 63,
      "rank": 63,
      "htf_score": 40.7,
      "ltf_score": -16.9,
      "daily_structure": {
        "px": 489.96,
        "e21": 486.78,
        "e48": 483.15,
        "e200": 468.57,
        "pct_above_e48": 1.41,
        "pct_above_e21": 0.65,
        "e21_slope_5d_pct": 0.62,
        "e48_slope_10d_pct": 0.54,
        "bull_stack": true,
        "bear_stack": false,
        "above_e200": true
      },
      "index_etf_swing_diag": null
    },
    {
      "ticker": "IWM",
      "ts": 1767814200000,
      "reason": "h3_rank_below_transitional_floor",
      "kanban_stage": "watch",
      "state": "HTF_BULL_LTF_BULL",
      "score": 88,
      "rank": 88,
      "htf_score": 41.4,
      "ltf_score": 0.5,
      "daily_structure": {
        "px": 255.48,
        "e21": 251.93,
        "e48": 250.29,
        "e200": 241.86,
        "pct_above_e48": 2.07,
        "pct_above_e21": 1.41,
        "e21_slope_5d_pct": 0.81,
        "e48_slope_10d_pct": 0.41,
        "bull_stack": true,
        "bear_stack": false,
        "above_e200": true
      },
      "index_etf_swing_diag": null
    },
    {
      "ticker": "DIA",
      "ts": 1767814200000,
      "reason": "h3_rank_below_transitional_floor",
      "kanban_stage": "watch",
      "state": "HTF_BULL_LTF_PULLBACK",
      "score": 70,
      "rank": 70,
      "htf_score": 40.7,
      "ltf_score": -19.3,
      "daily_structure": {
        "px": 489.96,
        "e21": 486.78,
        "e48": 483.15,
        "e200": 468.57,
        "pct_above_e48": 1.41,
        "pct_above_e21": 0.65,
        "e21_slope_5d_pct": 0.62,
        "e48_slope_10d_pct": 0.54,
        "bull_stack": true,
        "bear_stack": false,
        "above_e200": true
      },
      "index_etf_swing_diag": null
    },
    {
      "ticker": "SPY",
      "ts": 1767816000000,
      "reason": "h3_rank_below_transitional_floor",
      "kanban_stage": "watch",
      "state": "HTF_BULL_LTF_PULLBACK",
      "score": 87,
      "rank": 87,
      "htf_score": 43.4,
      "ltf_score": -12.9,
      "daily_structure": {
        "px": 689.58,
        "e21": 686.97,
        "e48": 684.15,
        "e200": 666.21,
        "pct_above_e48": 0.79,
        "pct_above_e21": 0.38,
        "e21_slope_5d_pct": 0.28,
        "e48_slope_10d_pct": 0.23,
        "bull_stack": true,
        "bear_stack": false,
        "above_e200": true
      },
      "index_etf_swing_diag": null
    },
    {
      "ticker": "QQQ",
      "ts": 1767819600000,
      "reason": "rvol_dead_zone",
      "kanban_stage": "watch",
      "state": "HTF_BULL_LTF_BULL",
      "score": 71,
      "rank": 71,
      "htf_score": 39.9,
      "ltf_score": 1.1,
      "daily_structure": {
        "px": 624.02,
        "e21": 619.48,
        "e48": 617.88,
        "e200": 600.71,
        "pct_above_e48": 0.99,
        "pct_above_e21": 0.73,
        "e21_slope_5d_pct": 0.33,
        "e48_slope_10d_pct": 0.1,
        "bull_stack": true,
        "bear_stack": false,
        "above_e200": true
      },
      "index_etf_swing_diag": null
    },
    {
      "ticker": "IWM",
      "ts": 1767819600000,
      "reason": "rvol_dead_zone",
      "kanban_stage": "watch",
      "state": "HTF_BULL_LTF_BULL",
      "score": 90,
      "rank": 90,
      "htf_score": 41.4,
      "ltf_score": 3.7,
      "daily_structure": {
        "px": 255.48,
        "e21": 251.93,
        "e48": 250.29,
        "e200": 241.86,
        "pct_above_e48": 2.07,
        "pct_above_e21": 1.41,
        "e21_slope_5d_pct": 0.81,
        "e48_slope_10d_pct": 0.41,
        "bull_stack": true,
        "bear_stack": false,
        "above_e200": true
      },
      "index_etf_swing_diag": null
    },
    {
      "ticker": "DIA",
      "ts": 1767819600000,
      "reason": "rvol_dead_zone",
      "kanban_stage": "watch",
      "state": "HTF_BULL_LTF_PULLBACK",
      "score": 77,
      "rank": 77,
      "htf_score": 40.7,
      "ltf_score": -21.7,
      "daily_structure": {
        "px": 489.96,
        "e21": 486.78,
        "e48": 483.15,
        "e200": 468.57,
        "pct_above_e48": 1.41,
        "pct_above_e21": 0.65,
        "e21_slope_5d_pct": 0.62,
        "e48_slope_10d_pct": 0.54,
        "bull_stack": true,
        "bear_stack": false,
        "above_e200": true
      },
      "index_etf_swing_diag": null
    }
  ],
  "blockChainCap": 100000,
  "fullDay": true
}