{
  "ok": true,
  "run_id": "phase-e2-slice-2025-11-v4",
  "count": 5,
  "trades": [
    {
      "trade_id": "QQQ-1762187400000",
      "run_id": "phase-e2-slice-2025-11-v4",
      "ticker": "QQQ",
      "direction": "LONG",
      "entry_ts": 1762187400000,
      "entry_price": 631.46,
      "rank": 93,
      "rr": 2.0925771476230106,
      "status": "LOSS",
      "exit_ts": 1762440300000,
      "exit_price": 620.7299,
      "exit_reason": "max_loss_time_scaled",
      "trimmed_pct": 0,
      "pnl": -203.91030310708504,
      "pnl_pct": -1.6992525258923752,
      "script_version": "alpaca_server_v2.0",
      "created_at": 1762187400000,
      "updated_at": 1776608284324,
      "trim_ts": null,
      "trim_price": null,
      "setup_name": null,
      "setup_grade": null,
      "risk_budget": null,
      "shares": null,
      "notional": null,
      "entry_path": null,
      "max_favorable_excursion": null,
      "max_adverse_excursion": null,
      "rank_trace_json": null
    },
    {
      "trade_id": "AAPL-1762961400000",
      "run_id": "phase-e2-slice-2025-11-v4",
      "ticker": "AAPL",
      "direction": "LONG",
      "entry_ts": 1762961400000,
      "entry_price": 274.24,
      "rank": 92,
      "rr": 2.738670694864046,
      "status": "WIN",
      "exit_ts": 1763145000000,
      "exit_price": 274.235,
      "exit_reason": "SMART_RUNNER_TRIM_REASSESS_ROUNDTRIP_FAILURE",
      "trimmed_pct": 0.5,
      "pnl": 32.86022060833359,
      "pnl_pct": 0.2743946907817961,
      "script_version": "alpaca_server_v2.0",
      "created_at": 1762961400000,
      "updated_at": 1776608284270,
      "trim_ts": 1763140200000,
      "trim_price": 275.75,
      "setup_name": null,
      "setup_grade": null,
      "risk_budget": null,
      "shares": null,
      "notional": null,
      "entry_path": null,
      "max_favorable_excursion": null,
      "max_adverse_excursion": null,
      "rank_trace_json": null
    },
    {
      "trade_id": "GOOGL-1763492400000",
      "run_id": "phase-e2-slice-2025-11-v4",
      "ticker": "GOOGL",
      "direction": "LONG",
      "entry_ts": 1763492400000,
      "entry_price": 288.265,
      "rank": 100,
      "rr": 5.087222647283881,
      "status": "WIN",
      "exit_ts": 1763671200000,
      "exit_price": 288.7,
      "exit_reason": "PROFIT_GIVEBACK_COOLING_HOLD",
      "trimmed_pct": 0.5,
      "pnl": 173.08556074711598,
      "pnl_pct": 1.444851091877273,
      "script_version": "alpaca_server_v2.0",
      "created_at": 1763492400000,
      "updated_at": 1776608284215,
      "trim_ts": 1763562600000,
      "trim_price": 296.16,
      "setup_name": null,
      "setup_grade": null,
      "risk_budget": null,
      "shares": null,
      "notional": null,
      "entry_path": null,
      "max_favorable_excursion": null,
      "max_adverse_excursion": null,
      "rank_trace_json": null
    },
    {
      "trade_id": "AGQ-1764088200000",
      "run_id": "phase-e2-slice-2025-11-v4",
      "ticker": "AGQ",
      "direction": "LONG",
      "entry_ts": 1764088200000,
      "entry_price": 87.34,
      "rank": 92,
      "rr": 7.460358056265991,
      "status": "WIN",
      "exit_ts": 1764342000000,
      "exit_price": 102.495,
      "exit_reason": "HARD_FUSE_RSI_EXTREME",
      "trimmed_pct": 0.5,
      "pnl": 1315.2317168979148,
      "pnl_pct": 10.960041218227612,
      "script_version": "alpaca_server_v2.0",
      "created_at": 1764088200000,
      "updated_at": 1776608284164,
      "trim_ts": 1764167400000,
      "trim_price": 91.33,
      "setup_name": null,
      "setup_grade": null,
      "risk_budget": null,
      "shares": null,
      "notional": null,
      "entry_path": null,
      "max_favorable_excursion": null,
      "max_adverse_excursion": null,
      "rank_trace_json": null
    },
    {
      "trade_id": "AAPL-1764352200000",
      "run_id": "phase-e2-slice-2025-11-v4",
      "ticker": "AAPL",
      "direction": "LONG",
      "entry_ts": 1764352200000,
      "entry_price": 278.86,
      "rank": 78,
      "rr": 3.4970873786407517,
      "status": "LOSS",
      "exit_ts": 1764536400000,
      "exit_price": 278.2225,
      "exit_reason": "replay_end_close",
      "trimmed_pct": 0,
      "pnl": -23.13195942523633,
      "pnl_pct": -2.3131959425236333,
      "script_version": "alpaca_server_v2.0",
      "created_at": 1764352200000,
      "updated_at": 1764536400000,
      "trim_ts": null,
      "trim_price": null,
      "setup_name": null,
      "setup_grade": null,
      "risk_budget": null,
      "shares": null,
      "notional": null,
      "entry_path": null,
      "max_favorable_excursion": null,
      "max_adverse_excursion": null,
      "rank_trace_json": null
    }
  ]
}